{
    "bannerURL": "URL de la pancarta",
    "avatarURL": "URL del avatar",
    "iconURL": "URL del icono",
    "sumbit": "Thanks for your sumbit , we will contact with you in the fastest time",
    "discommands": "Commands are disabled in this room ,  contact the admins to know the reason ",
    "blacklistBanWarning": "Está en la lista negra, contáctenos para apelar la lista negra.",
    "asciiMaxCaracters": "¡{0} caracteres como máximo!",
    "name": "Nombre",
    "nickname": "Apodo",
    "servers": "Servidores",
    "members": "miembros",
    "channels": "Canales",
    "creationDate": "Fecha de creación",
    "botInfosLanguages": "Idiomas admitidos",
    "InviteBOTDescription": "Do you want to test my luxury commands? , Invite me to your server",
    "userInfoDay": "día",
    "userInfoDays": "dias",
    "linkemojireply": "Please insert your chosen emojis!",
    "setdisabledcommands": "Please mention wanted channel to disable commands in it",
    "disabledcommands": "Comandos deshabilitados con éxito en {0}",
    "enablecommands": "Habilite correctamente los comandos en {0}",
    "helpCommandUsage": "uso :",
    "helpCommandExample": "Ejemplos:",
    "helpCommandAliases": "Alias:",
    "helpCommandPermissions": "permisos:",
    "helpPrefix": "Prefijo:",
    "vote": "Vote for our bot to encourage us to continue",
    "pingLatencyBot": "Latencia del bot:",
    "pingLatencyAPI": "Latencia de la API:",
    "configPrefixLengthMax": "Maximum prefix characters is `2` characters ",
    "configPrefixOld": "Prefijo antiguo:",
    "configPrefixNew": "Nuevo prefijo:",
    "configPrefixNotString": "¡El prefijo contiene solo letras o símbolos!",
    "configLangReply": "Los idiomas admitidos son árabe, turco e inglés; ayúdenos a respaldar el suyo en https://crowdin.com/project/valltdiscord",
    "configLangTooLong": "¡Los idiomas tienen solo 2 caracteres!",
    "configLangOld": "Idioma antiguo:",
    "configLangNew": "Nuevo idioma :",
    "configLangUnknown": "¡Este idioma no está disponible!",
    "configLangNotString": "¡Los idiomas solo contienen letras!",
    "configLogChannelOld": "Canal de registro antiguo:",
    "configLogChannelNew": "Nuevo canal de registro:",
    "messageEventMissingPerm1": "no tienes el",
    "messageEventMissingPerm2": "permiso para ejecutar este comando!",
    "messageEventBotMissingPerm1": "no tengo el",
    "messageEventBotMissingPerm2": "permiso para ejecutar este comando!",
    "messageEventCommandNeedArg1": "Necesitas",
    "messageEventCommandNeedArg2one": "argumento para este comando,",
    "messageEventCommandNeedArg2multiple": "argumentos para este comando,",
    "EcoBioNewBio": "Nuevo",
    "errorMessage": "Ocurrió un error:",
    "errorUserNotFound": "¡No pude encontrar a este usuario!",
    "errorChannelNotFound": "¡No pude encontrar este canal!",
    "errorHarmYourself1": "no puedes",
    "errorHarmYourself2": "tú mismo !",
    "noBannerUser": "*{0}** no tiene banner",
    "noBannerYou": "no tienes pancarta",
    "noCommandAliases": "No hay alias para este comando.",
    "botsNoBanner": "🧐 ¡Los bots no tienen banner!",
    "onlyowner": ":x: Solo la propiedad de este servidor puede usar este comando",
    "onlydevs": ": x: Solo los desarrolladores pueden usar este comando",
    "donevolume": "`🔊` | **Cambiar volumen a:** **{0}%**",
    "nofoundmusic": "¡No se ha encontrado ningún resultado para {0}!",
    "botinfo": {
        "servers": "Servidores",
        "users": "Usuarios",
        "channels": "Canales",
        "uptime": "tiempo de actividad",
        "createdAt": "Creado en",
        "ram": "RAM"
    },
    "tickets": {
        "open": "El soporte estará contigo en breve.\nPara cerrar este ticket haz clic en el botón 🔒",
        "butclose": "Cerrar",
        "butcancel": "Cancelar",
        "butdelete": "Borrar",
        "wait": "Creando ticket, por favor espere...",
        "sure": "¿Está seguro de que desea cerrar este ticket?",
        "delete": "El ticket se eliminará en unos segundos.",
        "created": "Ticket creado",
        "closed": "Ticket cerrado por",
        "onlysupport": ":x: Solo soporte puede borrar este ticket",
        "youneed": ":x: primero debe configurar los boletos por uso"
    },
    "music": {
        "song": "Proporcione un nombre de canción o un enlace.",
        "joinvoice": "Tienes que estar en un canal mismo/de voz.",
        "noqueue": "¡No hay nada en la cola ahora mismo!",
        "searching": "Buscando.....",
        "processing": "Procesando.....",
        "loop": "`🔁` | **La canción está en bucle:** Actual",
        "unloop": "`🔁` | **La canción se libera:** Actual",
        "youtube": {
            "uploader": "Subidor:",
            "requester": "Solicitante:",
            "volume": "Volumen:",
            "views": "Puntos de vista:",
            "likes": "Gustos:"
        }
    },
    "volume": {
        "vol": "`Actual` **volumen**: **{0}%**",
        "enternumber": "por favor ingrese un número valido",
        "only100": "Por favor proporcione un número entre 1 y 100"
    },
    "skip": {
        "noqueue": "`🚨` | **No hay** `Canciones` **en cola**",
        "done": "`⏭` | **La canción ha sido:** `Omitida`"
    }
}
